f5/__init__.py
f5/dispatch.py
f5/encoding.py
f5/filters.py
f5/handlers.py
f5/models.py
f5/nested_set.py
f5/services.py
f5/storage.py
test/__init__.py
test/test_handlers.py
f5-0.0.4.dist-info/LICENSE.txt
f5-0.0.4.dist-info/METADATA
f5-0.0.4.dist-info/WHEEL
f5-0.0.4.dist-info/top_level.txt
f5-0.0.4.dist-info/RECORD
